beautify/__init__.py
beautify/beautify.py
kmy_beautify-0.6.0.dist-info/METADATA
kmy_beautify-0.6.0.dist-info/WHEEL
kmy_beautify-0.6.0.dist-info/top_level.txt
kmy_beautify-0.6.0.dist-info/RECORD
