Metadata-Version: 2.1
Name: kmy-beautify
Version: 0.6.0
Summary: beautify the appearance of the terminal application.
Home-page: https://github.com/ExsoKamabay/kmy-beautify
Author: Exso Kamabay
License: Apache License 2.0
Keywords: kamabay,beautify,terminal,text,color,banner
Platform: UNKNOWN
Classifier: License :: OSI Approved :: Apache Software License
Classifier: Operating System :: OS Independent
Classifier: Programming Language :: Python :: 3
Classifier: Topic :: Utilities
Requires-Dist: art (==5.4)
Requires-Dist: bs4 (==0.0.1)
Requires-Dist: requests (==2.27.1)
Requires-Dist: shell (==1.0.1)
Requires-Dist: string-color (==1.2.1)
